torch_utils/__init__.py
torch_utils/__init__.pyi
torch_utils/datasets.py
torch_utils/callbacks/__init__.py
torch_utils/callbacks/__init__.pyi
torch_utils/callbacks/loops.py
mr_torch_utils-0.1.5.dist-info/METADATA
mr_torch_utils-0.1.5.dist-info/WHEEL
mr_torch_utils-0.1.5.dist-info/top_level.txt
mr_torch_utils-0.1.5.dist-info/RECORD
