Metadata-Version: 2.1
Name: mr-torch-utils
Version: 0.1.5
Summary: package_description
Author-email: Marcel Claramunt <marcel@moveread.com>
Project-URL: repo, https://github.com/moveread/REPO.git
Requires-Python: >=3.10
Requires-Dist: lazy-loader
